deepstack/__init__.py
deepstack/errors.py
deepstack/lazy_imports.py
deepstack/logging.py
deepstack/version.py
deepstack/components/__init__.py
deepstack/components/audio/__init__.py
deepstack/components/audio/whisper_local.py
deepstack/components/audio/whisper_remote.py
deepstack/components/builders/__init__.py
deepstack/components/builders/answer_builder.py
deepstack/components/builders/dynamic_chat_prompt_builder.py
deepstack/components/builders/dynamic_prompt_builder.py
deepstack/components/builders/prompt_builder.py
deepstack/components/caching/__init__.py
deepstack/components/caching/cache_checker.py
deepstack/components/classifiers/__init__.py
deepstack/components/classifiers/document_language_classifier.py
deepstack/components/connectors/__init__.py
deepstack/components/connectors/openapi_service.py
deepstack/components/converters/__init__.py
deepstack/components/converters/azure.py
deepstack/components/converters/html.py
deepstack/components/converters/markdown.py
deepstack/components/converters/openapi_functions.py
deepstack/components/converters/output_adapter.py
deepstack/components/converters/pdfminer.py
deepstack/components/converters/pypdf.py
deepstack/components/converters/tika.py
deepstack/components/converters/txt.py
deepstack/components/converters/utils.py
deepstack/components/embedders/__init__.py
deepstack/components/embedders/azure_document_embedder.py
deepstack/components/embedders/azure_text_embedder.py
deepstack/components/embedders/hugging_face_api_document_embedder.py
deepstack/components/embedders/hugging_face_api_text_embedder.py
deepstack/components/embedders/hugging_face_tei_document_embedder.py
deepstack/components/embedders/hugging_face_tei_text_embedder.py
deepstack/components/embedders/openai_document_embedder.py
deepstack/components/embedders/openai_text_embedder.py
deepstack/components/embedders/sentence_transformers_document_embedder.py
deepstack/components/embedders/sentence_transformers_text_embedder.py
deepstack_ai-2.2.0rc0.dist-info/METADATA
deepstack_ai-2.2.0rc0.dist-info/WHEEL
deepstack_ai-2.2.0rc0.dist-info/licenses/LICENSE
deepstack_ai-2.2.0rc0.dist-info/RECORD
