Metadata-Version: 2.3
Name: deepstack-ai
Version: 2.2.0rc0
Summary: LLM framework to build customizable, production-ready LLM applications. Connect components (models, vector DBs, file converters) to pipelines or agents that can interact with your data.
Project-URL: CI: GitHub, https://github.com/khulnasoft/deepstack/actions
Project-URL: Docs: RTD, https://deepstack.khulnasoft.com/overview/intro
Project-URL: GitHub: issues, https://github.com/khulnasoft/deepstack/issues
Project-URL: GitHub: repo, https://github.com/khulnasoft/deepstack
Project-URL: Homepage, https://github.com/khulnasoft/deepstack
Author-email: "khulnasoft.com" <info@khulnasoft.com>
License-Expression: Apache-2.0
License-File: LICENSE
Keywords: BERT,QA,Question-Answering,Reader,Retriever,albert,language-model,mrc,roberta,search,semantic-search,squad,transfer-learning,transformer
Classifier: Development Status :: 5 - Production/Stable
Classifier: Intended Audience :: Science/Research
Classifier: License :: Freely Distributable
Classifier: License :: OSI Approved :: Apache Software License
Classifier: Operating System :: OS Independent
Classifier: Programming Language :: Python
Classifier: Programming Language :: Python :: 3
Classifier: Programming Language :: Python :: 3.8
Classifier: Programming Language :: Python :: 3.9
Classifier: Programming Language :: Python :: 3.10
Classifier: Topic :: Scientific/Engineering :: Artificial Intelligence
Requires-Python: >=3.8
Requires-Dist: boilerpy3
Requires-Dist: jinja2
Requires-Dist: lazy-imports
Requires-Dist: more-itertools
Requires-Dist: networkx
Requires-Dist: numpy
Requires-Dist: openai>=1.1.0
Requires-Dist: pandas
Requires-Dist: posthog
Requires-Dist: python-dateutil
Requires-Dist: pyyaml
Requires-Dist: requests
Requires-Dist: tenacity
Requires-Dist: tqdm
Requires-Dist: typing-extensions>=4.7
